cleanlab_studio/__init__.py
cleanlab_studio/errors.py
cleanlab_studio/version.py
cleanlab_studio/cli/__init__.py
cleanlab_studio/cli/api_service.py
cleanlab_studio/cli/click_helpers.py
cleanlab_studio/cli/main.py
cleanlab_studio/cli/types.py
cleanlab_studio/cli/util.py
cleanlab_studio/cli/classes/__init__.py
cleanlab_studio/cli/classes/csv_dataset.py
cleanlab_studio/cli/classes/dataset.py
cleanlab_studio/cli/classes/excel_dataset.py
cleanlab_studio/cli/classes/json_dataset.py
cleanlab_studio/cli/cleanset/__init__.py
cleanlab_studio/cli/cleanset/commands.py
cleanlab_studio/cli/cleanset/download.py
cleanlab_studio/cli/cleanset/download_helpers.py
cleanlab_studio/cli/dataset/__init__.py
cleanlab_studio/cli/dataset/commands.py
cleanlab_studio/cli/dataset/schema_helpers.py
cleanlab_studio/cli/dataset/upload.py
cleanlab_studio/cli/decorators/__init__.py
cleanlab_studio/cli/decorators/auth_config.py
cleanlab_studio/cli/decorators/previous_state.py
cleanlab_studio/cli/login/__init__.py
cleanlab_studio/cli/login/login.py
cleanlab_studio/internal/__init__.py
cleanlab_studio/internal/clean_helpers.py
cleanlab_studio/internal/constants.py
cleanlab_studio/internal/deploy_helpers.py
cleanlab_studio/internal/enrichment_utils.py
cleanlab_studio/internal/settings.py
cleanlab_studio/internal/types.py
cleanlab_studio/internal/upload_helpers.py
cleanlab_studio/internal/util.py
cleanlab_studio/internal/api/__init__.py
cleanlab_studio/internal/api/api.py
cleanlab_studio/internal/api/api_helper.py
cleanlab_studio/internal/dataset_source/__init__.py
cleanlab_studio/internal/dataset_source/dataframe_dataset_source.py
cleanlab_studio/internal/dataset_source/dataset_source.py
cleanlab_studio/internal/dataset_source/filepath_dataset_source.py
cleanlab_studio/internal/dataset_source/pandas_dataset_source.py
cleanlab_studio/internal/dataset_source/pyspark_dataset_source.py
cleanlab_studio/internal/dataset_source/snowpark_dataset_source.py
cleanlab_studio/internal/tlm/__init__.py
cleanlab_studio-2.5.21.dist-info/LICENSE
cleanlab_studio-2.5.21.dist-info/METADATA
cleanlab_studio-2.5.21.dist-info/WHEEL
cleanlab_studio-2.5.21.dist-info/entry_points.txt
cleanlab_studio-2.5.21.dist-info/top_level.txt
cleanlab_studio-2.5.21.dist-info/RECORD
