Metadata-Version: 2.2
Name: cleanlab-studio
Version: 2.5.21
Summary: Client interface for all things Cleanlab Studio
Home-page: https://github.com/cleanlab/cleanlab-studio
Author: Cleanlab Inc
Author-email: team@cleanlab.ai
License: MIT
Project-URL: Bug Tracker, https://github.com/cleanlab/cleanlab-studio/issues
Project-URL: Documentation, https://help.cleanlab.ai
Keywords: cleanlab
Classifier: License :: OSI Approved :: MIT License
Classifier: Intended Audience :: Developers
Classifier: Intended Audience :: Education
Classifier: Intended Audience :: Science/Research
Classifier: Intended Audience :: Information Technology
Classifier: Natural Language :: English
Classifier: Programming Language :: Python :: 3
Classifier: Programming Language :: Python :: 3.8
Classifier: Programming Language :: Python :: 3.9
Classifier: Programming Language :: Python :: 3.10
Classifier: Topic :: Scientific/Engineering
Classifier: Topic :: Scientific/Engineering
Classifier: Topic :: Scientific/Engineering :: Mathematics
Classifier: Topic :: Scientific/Engineering :: Artificial Intelligence
Classifier: Operating System :: OS Independent
Requires-Python: >=3.8
License-File: LICENSE
Requires-Dist: aiohttp>=3.8.1
Requires-Dist: Click<8.2.0,>=8.1.0
Requires-Dist: colorama>=0.4.4
Requires-Dist: nest_asyncio>=1.5.0
Requires-Dist: pandas==2.*
Requires-Dist: pyexcel>=0.7.0
Requires-Dist: pyexcel-xls>=0.7.0
Requires-Dist: pyexcel-xlsx>=0.6.0
Requires-Dist: requests>=2.27.1
Requires-Dist: tqdm>=4.64.0
Requires-Dist: ijson>=3.1.4
Requires-Dist: jsonstreams>=0.6.0
Requires-Dist: semver<3.0.0,>=2.13.0
Requires-Dist: Pillow>=9.2.0
Requires-Dist: typing_extensions>=4.2.0
Requires-Dist: openpyxl!=3.1.0,>=3.0.0
Requires-Dist: validators>=0.20.0
Requires-Dist: matplotlib>=3.4.0
Dynamic: author
Dynamic: author-email
Dynamic: classifier
Dynamic: description
Dynamic: description-content-type
Dynamic: home-page
Dynamic: keywords
Dynamic: license
Dynamic: project-url
Dynamic: requires-dist
Dynamic: requires-python
Dynamic: summary
